data_visualizer/__init__.py
data_visualizer/__main__.py
data_visualizer_JavierRodriguezPosada-0.0.3.dist-info/LICENSE
data_visualizer_JavierRodriguezPosada-0.0.3.dist-info/METADATA
data_visualizer_JavierRodriguezPosada-0.0.3.dist-info/WHEEL
data_visualizer_JavierRodriguezPosada-0.0.3.dist-info/top_level.txt
data_visualizer_JavierRodriguezPosada-0.0.3.dist-info/RECORD
