Metadata-Version: 2.1
Name: data-visualizer-JavierRodriguezPosada
Version: 0.0.3
Summary: App for data visualization
Home-page: https://javiropos.visualstudio.com/DataVisualizer
Author: Javier Rodriguez Posada
Author-email: javiropos@gmail.com
License: UNKNOWN
Platform: UNKNOWN
Classifier: Programming Language :: Python :: 3
Classifier: License :: OSI Approved :: GNU Lesser General Public License v3 (LGPLv3)
Classifier: Operating System :: OS Independent
Requires-Python: >=3.8
Requires-Dist: numpy (==1.19.3)
Requires-Dist: xlrd (==1.2.0)
Requires-Dist: pandas (==1.1.4)
Requires-Dist: dash (==1.17.0)
